landingzone_organization/__init__.py
landingzone_organization/account.py
landingzone_organization/adapters/__init__.py
landingzone_organization/adapters/aws_organization.py
landingzone_organization/cli/__init__.py
landingzone_organization/cli/commands/__init__.py
landingzone_organization/cli/commands/account.py
landingzone_organization/cli/commands/export.py
landingzone_organization/cli/commands/organization.py
landingzone_organization/cli/commands/profiles.py
landingzone_organization/cli/commands/workload.py
landingzone_organization/cli/context.py
landingzone_organization/cli/handler.py
landingzone_organization/filtering.py
landingzone_organization/group.py
landingzone_organization/groups.py
landingzone_organization/organization.py
landingzone_organization/organization_unit.py
landingzone_organization/profile.py
landingzone_organization/profiles.py
landingzone_organization/schemas/__init__.py
landingzone_organization/schemas/environment.yaml
landingzone_organization/schemas/workload.yaml
landingzone_organization/workload.py
landingzone_organization/workload_generator.py
landingzone_organization/workloads.py
landingzone_organization-0.8.0.dist-info/LICENSE.txt
landingzone_organization-0.8.0.dist-info/METADATA
landingzone_organization-0.8.0.dist-info/WHEEL
landingzone_organization-0.8.0.dist-info/entry_points.txt
landingzone_organization-0.8.0.dist-info/RECORD
