Metadata-Version: 2.1
Name: landingzone-organization
Version: 0.8.0
Summary: 
Home-page: https://binxio.github.io/landingzone-organization/
Author: Joris Conijn
Author-email: Joris.Conijn@xebia.com
Requires-Python: >=3.9,<4.0
Classifier: Programming Language :: Python :: 3
Classifier: Programming Language :: Python :: 3.9
Classifier: Programming Language :: Python :: 3.10
Classifier: Programming Language :: Python :: 3.11
Requires-Dist: boto3 (>=1.26.83,<2.0.0)
Requires-Dist: click (>=8.1.3,<9.0.0)
Requires-Dist: jsonpickle (>=3.0.1,<4.0.0)
Requires-Dist: jsonschema (>=4.18.3,<5.0.0)
Project-URL: Documentation, https://binxio.github.io/landingzone-organization/3-user-documentation/
Project-URL: Repository, https://github.com/binxio/landingzone-organization
